lattice_explorer/__init__.py
lattice_explorer/__main__.py
lattice_explorer/explorer.py
lattice_explorer/parser.py
lattice_explorer/widgets.py
lattice_explorer-1.0.dist-info/LICENSE
lattice_explorer-1.0.dist-info/METADATA
lattice_explorer-1.0.dist-info/WHEEL
lattice_explorer-1.0.dist-info/top_level.txt
lattice_explorer-1.0.dist-info/RECORD
