Metadata-Version: 2.1
Name: lattice-explorer
Version: 1.0
Summary: Interactively explore MADX lattices by tweaking lattice parameters and observing the effect on lattice functions.
Home-page: https://gitlab.com/Dominik1123/lattice-explorer
Author: Dominik Vilsmeier
Author-email: d.vilsmeier@gsi.de
License: GPL-3.0
Keywords: MADX,lattice,visualization,interactive
Platform: UNKNOWN
Classifier: Development Status :: 4 - Beta
Classifier: Intended Audience :: Science/Research
Classifier: License :: OSI Approved :: GNU General Public License v3 or later (GPLv3+)
Classifier: Programming Language :: Python :: 3.7
Classifier: Programming Language :: Python :: 3.8
Classifier: Topic :: Scientific/Engineering :: Physics
Classifier: Topic :: Scientific/Engineering :: Visualization
Requires-Python: >=3.7
Requires-Dist: arguable
Requires-Dist: cpymad
Requires-Dist: matplotlib
Requires-Dist: numpy
Requires-Dist: PyQt5
